{
  "_meta": {
    "sources": [
      "loopback/common/models",
      "loopback/server/models",
      "../common/models",
      "./models",
      "../common/models/trip"
    ],
    "mixins": [
      "loopback/common/mixins",
      "loopback/server/mixins",
      "../common/mixins",
      "./mixins"
    ]
  },
  "User": {
    "dataSource": "db",
    "public": false
  },
  "AccessToken": {
    "dataSource": "db",
    "public": false
  },
  "ACL": {
    "dataSource": "db",
    "public": false
  },
  "Email": {
    "dataSource": "email"
  },
  "RoleMapping": {
    "dataSource": "db",
    "public": false
  },
  "Role": {
    "dataSource": "db",
    "public": false
  },
  "RbgRole": {
    "dataSource": "db",
    "public": false
  },
  "RbgUser": {
    "dataSource": "db",
    "public": true,
    "options": {
      "remoting": {
        "sharedMethods": {
          "*": false,
          "me": true
        }
      }
    }
  },

  "Adventure": {
    "dataSource": "db",
    "public": true
  },
  "AdventureFeed": {
    "dataSource": "db",
    "public": true
  },
  "AdventureUserMapping": {
    "dataSource": "db",
    "public": false
  },
  "Settings": {
    "dataSource": "db",
    "public": false
  },
  "Trip": {
    "dataSource": "db",
    "public": true,
    "options": {
      "remoting": {
        "sharedMethods": {
          "find": false
        }
      }
    }
  },
  "TripSwipe": {
    "dataSource": "db",
    "public": true,
    "options": {
      "remoting": {
        "sharedMethods": {
          "create": false
        }
      }
    }
  }
}